[{"ID":1,"Age":35,"Area Income":61833.9},{"ID":2,"Age":31,"Area Income":68441.85},{"ID":3,"Age":26,"Area Income":59785.94},{"ID":4,"Age":29,"Area Income":54806.18},{"ID":5,"Age":35,"Area Income":73889.99},{"ID":6,"Age":23,"Area Income":59761.56},{"ID":7,"Age":33,"Area Income":53852.85},{"ID":8,"Age":48,"Area Income":24593.33},{"ID":9,"Age":30,"Area Income":68862},{"ID":10,"Age":20,"Area Income":55642.32},{"ID":11,"Age":49,"Area Income":45632.51},{"ID":12,"Age":37,"Area Income":62491.01},{"ID":13,"Age":48,"Area Income":51636.92},{"ID":14,"Age":24,"Area Income":51739.63},{"ID":15,"Age":33,"Area Income":30976},{"ID":16,"Age":23,"Area Income":52182.23},{"ID":17,"Age":37,"Area Income":23936.86},{"ID":18,"Age":41,"Area Income":71511.08},{"ID":19,"Age":36,"Area Income":31087.54},{"ID":20,"Age":40,"Area Income":23821.72},{"ID":21,"Age":30,"Area Income":64802.33},{"ID":22,"Age":35,"Area Income":60015.57},{"ID":23,"Age":52,"Area Income":32635.7},{"ID":24,"Age":36,"Area Income":61628.72},{"ID":25,"Age":41,"Area Income":68962.32},{"ID":26,"Age":28,"Area Income":64828},{"ID":27,"Age":28,"Area Income":38067.08},{"ID":28,"Age":52,"Area Income":58295.82},{"ID":29,"Age":34,"Area Income":32708.94},{"ID":30,"Age":22,"Area Income":46179.97},{"ID":31,"Age":35,"Area Income":51473.28},{"ID":32,"Age":28,"Area Income":45593.93},{"ID":33,"Age":57,"Area Income":25583.29},{"ID":34,"Age":23,"Area Income":30227.98},{"ID":35,"Age":57,"Area Income":45580.92},{"ID":36,"Age":30,"Area Income":61389.5},{"ID":37,"Age":53,"Area Income":56770.79},{"ID":38,"Age":39,"Area Income":76435.3},{"ID":39,"Age":46,"Area Income":57425.87},{"ID":40,"Age":39,"Area Income":27508.41},{"ID":41,"Age":29,"Area Income":57691.95},{"ID":42,"Age":30,"Area Income":59784.18},{"ID":43,"Age":32,"Area Income":66572.39},{"ID":44,"Age":31,"Area Income":64929.61},{"ID":45,"Age":25,"Area Income":57519.64},{"ID":46,"Age":52,"Area Income":53575.48},{"ID":47,"Age":20,"Area Income":50983.75},{"ID":48,"Age":43,"Area Income":67058.72},{"ID":49,"Age":37,"Area Income":52723.34},{"ID":50,"Age":46,"Area Income":54286.1},{"ID":51,"Age":23,"Area Income":61526.25},{"ID":52,"Age":28,"Area Income":58526.04},{"ID":53,"Age":45,"Area Income":53350.11},{"ID":54,"Age":50,"Area Income":62657.53},{"ID":55,"Age":47,"Area Income":62722.57},{"ID":56,"Age":31,"Area Income":67479.62},{"ID":57,"Age":36,"Area Income":75254.88},{"ID":58,"Age":49,"Area Income":52336.64},{"ID":59,"Age":29,"Area Income":56113.37},{"ID":60,"Age":41,"Area Income":24852.9},{"ID":61,"Age":27,"Area Income":47708.42},{"ID":62,"Age":34,"Area Income":64654.66},{"ID":63,"Age":29,"Area Income":71228.44},{"ID":64,"Age":32,"Area Income":61601.05},{"ID":65,"Age":45,"Area Income":66281.46},{"ID":66,"Age":29,"Area Income":73910.9},{"ID":67,"Age":40,"Area Income":51317.33},{"ID":68,"Age":32,"Area Income":51510.18},{"ID":69,"Age":25,"Area Income":61005.87},{"ID":70,"Age":34,"Area Income":32536.98},{"ID":71,"Age":31,"Area Income":60248.97},{"ID":72,"Age":46,"Area Income":74543.81},{"ID":73,"Age":39,"Area Income":75509.61},{"ID":74,"Age":43,"Area Income":42650.32},{"ID":75,"Age":42,"Area Income":58183.04},{"ID":76,"Age":22,"Area Income":60465.72},{"ID":77,"Age":35,"Area Income":57009.76},{"ID":78,"Age":33,"Area Income":54541.56},{"ID":79,"Age":38,"Area Income":32689.04},{"ID":80,"Age":45,"Area Income":55605.92},{"ID":81,"Age":27,"Area Income":63296.87},{"ID":82,"Age":28,"Area Income":65653.47},{"ID":83,"Age":38,"Area Income":61652.53},{"ID":84,"Age":54,"Area Income":30726.26},{"ID":85,"Age":31,"Area Income":74535.94},{"ID":86,"Age":41,"Area Income":47861.93},{"ID":87,"Age":36,"Area Income":73600.28},{"ID":88,"Age":34,"Area Income":58543.94},{"ID":89,"Age":34,"Area Income":42696.67},{"ID":90,"Age":37,"Area Income":37334.78},{"ID":91,"Age":43,"Area Income":71392.53},{"ID":92,"Age":24,"Area Income":59550.05},{"ID":93,"Age":26,"Area Income":64264.25},{"ID":94,"Age":40,"Area Income":64147.86},{"ID":95,"Age":31,"Area Income":25686.34},{"ID":96,"Age":26,"Area Income":52968.22},{"ID":97,"Age":36,"Area Income":22473.08},{"ID":98,"Age":41,"Area Income":64927.19},{"ID":99,"Age":46,"Area Income":51868.85},{"ID":100,"Age":34,"Area Income":69456.83},{"ID":101,"Age":53,"Area Income":31947.65},{"ID":102,"Age":23,"Area Income":51864.77},{"ID":103,"Age":40,"Area Income":59593.56},{"ID":104,"Age":21,"Area Income":48376.14},{"ID":105,"Age":20,"Area Income":56884.74},{"ID":106,"Age":40,"Area Income":67186.54},{"ID":107,"Age":25,"Area Income":46557.92},{"ID":108,"Age":42,"Area Income":66541.05},{"ID":109,"Age":30,"Area Income":33258.09},{"ID":110,"Age":32,"Area Income":72272.9},{"ID":111,"Age":50,"Area Income":60333.38},{"ID":112,"Age":53,"Area Income":65229.13},{"ID":113,"Age":22,"Area Income":56067.38},{"ID":114,"Age":46,"Area Income":37838.72},{"ID":115,"Age":32,"Area Income":72683.35},{"ID":116,"Age":31,"Area Income":56729.78},{"ID":117,"Age":55,"Area Income":66815.54},{"ID":118,"Age":42,"Area Income":60223.52},{"ID":119,"Age":50,"Area Income":29727.79},{"ID":120,"Age":45,"Area Income":49269.98},{"ID":121,"Age":31,"Area Income":57669.41},{"ID":122,"Age":26,"Area Income":56791.75},{"ID":123,"Age":27,"Area Income":63274.88},{"ID":124,"Age":36,"Area Income":35466.8},{"ID":125,"Age":43,"Area Income":68787.09},{"ID":126,"Age":31,"Area Income":61227.59},{"ID":127,"Age":44,"Area Income":56366.88},{"ID":128,"Age":45,"Area Income":57868.44},{"ID":129,"Age":27,"Area Income":66618.21},{"ID":130,"Age":37,"Area Income":73104.47},{"ID":131,"Age":50,"Area Income":21644.91},{"ID":132,"Age":36,"Area Income":53817.02},{"ID":133,"Age":36,"Area Income":76368.31},{"ID":134,"Age":29,"Area Income":67633.44},{"ID":135,"Age":47,"Area Income":50335.46},{"ID":136,"Age":39,"Area Income":17709.98},{"ID":137,"Age":36,"Area Income":41229.16},{"ID":138,"Age":38,"Area Income":42581.23},{"ID":139,"Age":23,"Area Income":61617.98},{"ID":140,"Age":38,"Area Income":70575.6},{"ID":141,"Age":31,"Area Income":64122.36},{"ID":142,"Age":30,"Area Income":52097.32},{"ID":143,"Age":44,"Area Income":65953.76},{"ID":144,"Age":44,"Area Income":60192.72},{"ID":145,"Age":41,"Area Income":77460.07},{"ID":146,"Age":44,"Area Income":45716.48},{"ID":147,"Age":49,"Area Income":65120.86},{"ID":148,"Age":41,"Area Income":49995.63},{"ID":149,"Age":46,"Area Income":71718.51},{"ID":150,"Age":57,"Area Income":61770.34},{"ID":151,"Age":25,"Area Income":69112.84},{"ID":152,"Age":35,"Area Income":72524.86},{"ID":153,"Age":48,"Area Income":36782.38},{"ID":154,"Age":33,"Area Income":66699.12},{"ID":155,"Age":27,"Area Income":64287.78},{"ID":156,"Age":38,"Area Income":56637.59},{"ID":157,"Age":36,"Area Income":55787.58},{"ID":158,"Age":28,"Area Income":61142.33},{"ID":159,"Age":27,"Area Income":61625.87},{"ID":160,"Age":36,"Area Income":73234.87},{"ID":161,"Age":35,"Area Income":74166.24},{"ID":162,"Age":33,"Area Income":62669.59},{"ID":163,"Age":31,"Area Income":57756.89},{"ID":164,"Age":24,"Area Income":58019.64},{"ID":165,"Age":50,"Area Income":50960.08},{"ID":166,"Age":32,"Area Income":48246.6},{"ID":167,"Age":55,"Area Income":28271.84},{"ID":168,"Age":31,"Area Income":53767.12},{"ID":169,"Age":42,"Area Income":43662.1},{"ID":170,"Age":34,"Area Income":62238.58},{"ID":171,"Age":52,"Area Income":49030.03},{"ID":172,"Age":47,"Area Income":76003.47},{"ID":173,"Age":31,"Area Income":68094.85},{"ID":174,"Age":26,"Area Income":64395.85},{"ID":175,"Age":48,"Area Income":70053.27},{"ID":176,"Age":35,"Area Income":72423.97},{"ID":177,"Age":44,"Area Income":42995.8},{"ID":178,"Age":22,"Area Income":60309.58},{"ID":179,"Age":31,"Area Income":38349.78},{"ID":180,"Age":34,"Area Income":63115.34},{"ID":181,"Age":38,"Area Income":31343.39},{"ID":182,"Age":27,"Area Income":40763.13},{"ID":183,"Age":50,"Area Income":36752.24},{"ID":184,"Age":41,"Area Income":65044.59},{"ID":185,"Age":29,"Area Income":53673.08},{"ID":186,"Age":54,"Area Income":43444.86},{"ID":187,"Age":57,"Area Income":44248.52},{"ID":188,"Age":31,"Area Income":62572.88},{"ID":189,"Age":30,"Area Income":39840.55},{"ID":190,"Age":36,"Area Income":32593.59},{"ID":191,"Age":30,"Area Income":41629.86},{"ID":192,"Age":35,"Area Income":43313.73},{"ID":193,"Age":49,"Area Income":42993.48},{"ID":194,"Age":53,"Area Income":46004.31},{"ID":195,"Age":33,"Area Income":49325.48},{"ID":196,"Age":32,"Area Income":51633.34},{"ID":197,"Age":45,"Area Income":63363.04},{"ID":198,"Age":36,"Area Income":64045.93},{"ID":199,"Age":31,"Area Income":73049.3},{"ID":200,"Age":27,"Area Income":66624.6},{"ID":201,"Age":40,"Area Income":77567.85},{"ID":202,"Age":29,"Area Income":53431.35},{"ID":203,"Age":40,"Area Income":31265.75},{"ID":204,"Age":31,"Area Income":74780.74},{"ID":205,"Age":29,"Area Income":70410.11},{"ID":206,"Age":29,"Area Income":37345.24},{"ID":207,"Age":28,"Area Income":66107.84},{"ID":208,"Age":30,"Area Income":62336.39},{"ID":209,"Age":58,"Area Income":39132.64},{"ID":210,"Age":38,"Area Income":38745.29},{"ID":211,"Age":28,"Area Income":65172.22},{"ID":212,"Age":38,"Area Income":68519.96},{"ID":213,"Age":27,"Area Income":54774.77},{"ID":214,"Age":43,"Area Income":76246.96},{"ID":215,"Age":40,"Area Income":65461.92},{"ID":216,"Age":23,"Area Income":34127.21},{"ID":217,"Age":53,"Area Income":35253.98},{"ID":218,"Age":34,"Area Income":44893.71},{"ID":219,"Age":40,"Area Income":59621.02},{"ID":220,"Age":38,"Area Income":20856.54},{"ID":221,"Age":37,"Area Income":55353.41},{"ID":222,"Age":27,"Area Income":67516.07},{"ID":223,"Age":39,"Area Income":68737.75},{"ID":224,"Age":41,"Area Income":76893.84},{"ID":225,"Age":42,"Area Income":59886.58},{"ID":226,"Age":30,"Area Income":53441.69},{"ID":227,"Age":29,"Area Income":41356.31},{"ID":228,"Age":38,"Area Income":49942.66},{"ID":229,"Age":31,"Area Income":74430.08},{"ID":230,"Age":23,"Area Income":58633.63},{"ID":231,"Age":33,"Area Income":72707.87},{"ID":232,"Age":32,"Area Income":31092.93},{"ID":233,"Age":38,"Area Income":74445.18},{"ID":234,"Age":28,"Area Income":49309.14},{"ID":235,"Age":50,"Area Income":56735.14},{"ID":236,"Age":45,"Area Income":40183.75},{"ID":237,"Age":36,"Area Income":58348.41},{"ID":238,"Age":30,"Area Income":72209.99},{"ID":239,"Age":33,"Area Income":62060.11},{"ID":240,"Age":32,"Area Income":67113.46},{"ID":241,"Age":44,"Area Income":24030.06},{"ID":242,"Age":47,"Area Income":56180.93},{"ID":243,"Age":32,"Area Income":62204.93},{"ID":244,"Age":30,"Area Income":60372.64},{"ID":245,"Age":24,"Area Income":65280.16},{"ID":246,"Age":53,"Area Income":34309.24},{"ID":247,"Age":45,"Area Income":59610.81},{"ID":248,"Age":41,"Area Income":50278.89},{"ID":249,"Age":56,"Area Income":43450.11},{"ID":250,"Age":25,"Area Income":25408.21},{"ID":251,"Age":36,"Area Income":71136.49},{"ID":252,"Age":45,"Area Income":63883.81},{"ID":253,"Age":33,"Area Income":64902.47},{"ID":254,"Age":30,"Area Income":66784.81},{"ID":255,"Age":48,"Area Income":62784.85},{"ID":256,"Age":28,"Area Income":63727.5},{"ID":257,"Age":32,"Area Income":61608.23},{"ID":258,"Age":38,"Area Income":56782.18},{"ID":259,"Age":39,"Area Income":64447.77},{"ID":260,"Age":31,"Area Income":42042.95},{"ID":261,"Age":28,"Area Income":67669.06},{"ID":262,"Age":35,"Area Income":54875.95},{"ID":263,"Age":35,"Area Income":73347.67},{"ID":264,"Age":44,"Area Income":50199.77},{"ID":265,"Age":38,"Area Income":50723.67},{"ID":266,"Age":43,"Area Income":63450.96},{"ID":267,"Age":26,"Area Income":56694.12},{"ID":268,"Age":34,"Area Income":70547.16},{"ID":269,"Age":26,"Area Income":47391.95},{"ID":270,"Age":26,"Area Income":62312.23},{"ID":271,"Age":53,"Area Income":63100.13},{"ID":272,"Age":37,"Area Income":73687.5},{"ID":273,"Age":33,"Area Income":52686.47},{"ID":274,"Age":37,"Area Income":78119.5},{"ID":275,"Age":28,"Area Income":57014.84},{"ID":276,"Age":29,"Area Income":27086.4},{"ID":277,"Age":35,"Area Income":58337.18},{"ID":278,"Age":32,"Area Income":50216.01},{"ID":279,"Age":26,"Area Income":53049.44},{"ID":280,"Age":28,"Area Income":62927.96},{"ID":281,"Age":52,"Area Income":32847.53},{"ID":282,"Age":24,"Area Income":32006.82},{"ID":283,"Age":35,"Area Income":48913.07},{"ID":284,"Age":35,"Area Income":69285.69},{"ID":285,"Age":51,"Area Income":53700.57},{"ID":286,"Age":22,"Area Income":52011},{"ID":287,"Age":26,"Area Income":46339.25},{"ID":288,"Age":37,"Area Income":67938.77},{"ID":289,"Age":42,"Area Income":66348.95},{"ID":290,"Age":24,"Area Income":66873.9},{"ID":291,"Age":31,"Area Income":72270.88},{"ID":292,"Age":32,"Area Income":61610.05},{"ID":293,"Age":39,"Area Income":76560.59},{"ID":294,"Age":33,"Area Income":62667.51},{"ID":295,"Age":36,"Area Income":75687.46},{"ID":296,"Age":36,"Area Income":66744.65},{"ID":297,"Age":35,"Area Income":67714.82},{"ID":298,"Age":31,"Area Income":69710.51},{"ID":299,"Age":31,"Area Income":66269.49},{"ID":300,"Age":25,"Area Income":60843.32},{"ID":301,"Age":28,"Area Income":55041.6},{"ID":302,"Age":50,"Area Income":73863.25},{"ID":303,"Age":39,"Area Income":62378.05},{"ID":304,"Age":38,"Area Income":63336.85},{"ID":305,"Age":43,"Area Income":42191.61},{"ID":306,"Age":24,"Area Income":56194.56},{"ID":307,"Age":33,"Area Income":61771.9},{"ID":308,"Age":35,"Area Income":61383.79},{"ID":309,"Age":32,"Area Income":63924.82},{"ID":310,"Age":54,"Area Income":23975.35},{"ID":311,"Age":34,"Area Income":70179.11},{"ID":312,"Age":49,"Area Income":66524.8},{"ID":313,"Age":22,"Area Income":41851.38},{"ID":314,"Age":33,"Area Income":61275.18},{"ID":315,"Age":41,"Area Income":60638.38},{"ID":316,"Age":39,"Area Income":47160.53},{"ID":317,"Age":21,"Area Income":48537.18},{"ID":318,"Age":25,"Area Income":53058.91},{"ID":319,"Age":31,"Area Income":68614.98},{"ID":320,"Age":44,"Area Income":44174.25},{"ID":321,"Age":34,"Area Income":67050.16},{"ID":322,"Age":37,"Area Income":54520.14},{"ID":323,"Age":30,"Area Income":54952.42},{"ID":324,"Age":35,"Area Income":69476.42},{"ID":325,"Age":41,"Area Income":54989.93},{"ID":326,"Age":36,"Area Income":29398.61},{"ID":327,"Age":48,"Area Income":42861.42},{"ID":328,"Age":32,"Area Income":65883.39},{"ID":329,"Age":25,"Area Income":65421.39},{"ID":330,"Age":31,"Area Income":60953.93},{"ID":331,"Age":26,"Area Income":58476.57},{"ID":332,"Age":31,"Area Income":66636.84},{"ID":333,"Age":49,"Area Income":67430.96},{"ID":334,"Age":34,"Area Income":57260.41},{"ID":335,"Age":40,"Area Income":66359.32},{"ID":336,"Age":41,"Area Income":57587},{"ID":337,"Age":35,"Area Income":63060.55},{"ID":338,"Age":28,"Area Income":59998.5},{"ID":339,"Age":40,"Area Income":74024.61},{"ID":340,"Age":22,"Area Income":60550.66},{"ID":341,"Age":47,"Area Income":57983.3},{"ID":342,"Age":48,"Area Income":52736.33},{"ID":343,"Age":38,"Area Income":46653.75},{"ID":344,"Age":28,"Area Income":56986.73},{"ID":345,"Age":26,"Area Income":55336.18},{"ID":346,"Age":21,"Area Income":42162.9},{"ID":347,"Age":25,"Area Income":39699.13},{"ID":348,"Age":52,"Area Income":56394.82},{"ID":349,"Age":37,"Area Income":75044.35},{"ID":350,"Age":19,"Area Income":53309.61},{"ID":351,"Age":28,"Area Income":58996.12},{"ID":352,"Age":23,"Area Income":56605.12},{"ID":353,"Age":30,"Area Income":62475.99},{"ID":354,"Age":44,"Area Income":70492.6},{"ID":355,"Age":52,"Area Income":43698.53},{"ID":356,"Age":36,"Area Income":57737.51},{"ID":357,"Age":47,"Area Income":31281.01},{"ID":358,"Age":39,"Area Income":45800.48},{"ID":359,"Age":59,"Area Income":42362.49},{"ID":360,"Age":34,"Area Income":66691.23},{"ID":361,"Age":33,"Area Income":56369.74},{"ID":362,"Age":41,"Area Income":59397.89},{"ID":363,"Age":28,"Area Income":66025.11},{"ID":364,"Age":36,"Area Income":68211.35},{"ID":365,"Age":42,"Area Income":73608.99},{"ID":366,"Age":54,"Area Income":61228.96},{"ID":367,"Age":29,"Area Income":72325.91},{"ID":368,"Age":40,"Area Income":44559.43},{"ID":369,"Age":36,"Area Income":73207.15},{"ID":370,"Age":25,"Area Income":46722.07},{"ID":371,"Age":50,"Area Income":45400.5},{"ID":372,"Age":45,"Area Income":41417.27},{"ID":373,"Age":26,"Area Income":60845.55},{"ID":374,"Age":47,"Area Income":60812.77},{"ID":375,"Age":25,"Area Income":64267.88},{"ID":376,"Age":24,"Area Income":58151.87},{"ID":377,"Age":37,"Area Income":52079.18},{"ID":378,"Age":42,"Area Income":26023.99},{"ID":379,"Age":31,"Area Income":62318.38},{"ID":380,"Age":39,"Area Income":56216.57},{"ID":381,"Age":30,"Area Income":61806.31},{"ID":382,"Age":41,"Area Income":51662.24},{"ID":383,"Age":29,"Area Income":67080.94},{"ID":384,"Age":26,"Area Income":51975.41},{"ID":385,"Age":27,"Area Income":28019.09},{"ID":386,"Age":37,"Area Income":67744.56},{"ID":387,"Age":33,"Area Income":66574},{"ID":388,"Age":42,"Area Income":30487.48},{"ID":389,"Age":40,"Area Income":74903.41},{"ID":390,"Age":38,"Area Income":19991.72},{"ID":391,"Age":36,"Area Income":66050.63},{"ID":392,"Age":44,"Area Income":70449.04},{"ID":393,"Age":28,"Area Income":64008.55},{"ID":394,"Age":26,"Area Income":70203.74},{"ID":395,"Age":47,"Area Income":27262.51},{"ID":396,"Age":20,"Area Income":49544.41},{"ID":397,"Age":51,"Area Income":28357.27},{"ID":398,"Age":28,"Area Income":66929.03},{"ID":399,"Age":40,"Area Income":75524.78},{"ID":400,"Age":27,"Area Income":66265.34},{"ID":401,"Age":47,"Area Income":55993.68},{"ID":402,"Age":34,"Area Income":56379.3},{"ID":403,"Age":43,"Area Income":31215.88},{"ID":404,"Age":29,"Area Income":51015.11},{"ID":405,"Age":52,"Area Income":46473.14},{"ID":406,"Age":41,"Area Income":55479.62},{"ID":407,"Age":50,"Area Income":68713.7},{"ID":408,"Age":27,"Area Income":34191.23},{"ID":409,"Age":49,"Area Income":51067.54},{"ID":410,"Age":45,"Area Income":46693.76},{"ID":411,"Age":33,"Area Income":19345.36},{"ID":412,"Age":29,"Area Income":66225.72},{"ID":413,"Age":20,"Area Income":38609.2},{"ID":414,"Age":40,"Area Income":37713.23},{"ID":415,"Age":39,"Area Income":63764.28},{"ID":416,"Age":43,"Area Income":41866.55},{"ID":417,"Age":32,"Area Income":57846.68},{"ID":418,"Age":29,"Area Income":69428.73},{"ID":419,"Age":24,"Area Income":60283.98},{"ID":420,"Age":43,"Area Income":79332.33},{"ID":421,"Age":41,"Area Income":53167.68},{"ID":422,"Age":45,"Area Income":64564.07},{"ID":423,"Age":35,"Area Income":60803.37},{"ID":424,"Age":31,"Area Income":28387.42},{"ID":425,"Age":36,"Area Income":58849.77},{"ID":426,"Age":42,"Area Income":65963.37},{"ID":427,"Age":37,"Area Income":75180.2},{"ID":428,"Age":33,"Area Income":61270.14},{"ID":429,"Age":29,"Area Income":56759.48},{"ID":430,"Age":31,"Area Income":46160.63},{"ID":431,"Age":32,"Area Income":43870.51},{"ID":432,"Age":35,"Area Income":50439.49},{"ID":433,"Age":43,"Area Income":28028.74},{"ID":434,"Age":36,"Area Income":64238.71},{"ID":435,"Age":39,"Area Income":65816.38},{"ID":436,"Age":42,"Area Income":72684.44},{"ID":437,"Age":27,"Area Income":38817.4},{"ID":438,"Age":27,"Area Income":63976.44},{"ID":439,"Age":36,"Area Income":37212.54},{"ID":440,"Age":23,"Area Income":52691.79},{"ID":441,"Age":32,"Area Income":65499.93},{"ID":442,"Age":35,"Area Income":63966.72},{"ID":443,"Age":39,"Area Income":52400.88},{"ID":444,"Age":38,"Area Income":49111.47},{"ID":445,"Age":40,"Area Income":41232.89},{"ID":446,"Age":32,"Area Income":52140.04},{"ID":447,"Age":34,"Area Income":60641.09},{"ID":448,"Age":44,"Area Income":74180.05},{"ID":449,"Age":50,"Area Income":51869.87},{"ID":450,"Age":22,"Area Income":48852.58},{"ID":451,"Age":28,"Area Income":59144.02},{"ID":452,"Age":24,"Area Income":33951.63},{"ID":453,"Age":34,"Area Income":58909.36},{"ID":454,"Age":25,"Area Income":49850.52},{"ID":455,"Age":52,"Area Income":28679.93},{"ID":456,"Age":33,"Area Income":69869.66},{"ID":457,"Age":35,"Area Income":48347.64},{"ID":458,"Age":25,"Area Income":45959.86},{"ID":459,"Age":42,"Area Income":70005.51},{"ID":460,"Age":26,"Area Income":51512.66},{"ID":461,"Age":40,"Area Income":25598.75},{"ID":462,"Age":45,"Area Income":49282.87},{"ID":463,"Age":27,"Area Income":67240.25},{"ID":464,"Age":52,"Area Income":42136.33},{"ID":465,"Age":45,"Area Income":62589.84},{"ID":466,"Age":33,"Area Income":67384.31},{"ID":467,"Age":35,"Area Income":25603.93},{"ID":468,"Age":23,"Area Income":39616},{"ID":469,"Age":47,"Area Income":28265.81},{"ID":470,"Age":25,"Area Income":63879.72},{"ID":471,"Age":36,"Area Income":70592.81},{"ID":472,"Age":37,"Area Income":76408.19},{"ID":473,"Age":24,"Area Income":55015.08},{"ID":474,"Age":29,"Area Income":51636.12},{"ID":475,"Age":31,"Area Income":29359.2},{"ID":476,"Age":33,"Area Income":71296.67},{"ID":477,"Age":24,"Area Income":46422.76},{"ID":478,"Age":50,"Area Income":52802},{"ID":479,"Age":41,"Area Income":59243.46},{"ID":480,"Age":28,"Area Income":35350.55},{"ID":481,"Age":22,"Area Income":59677.64},{"ID":482,"Age":40,"Area Income":70225.6},{"ID":483,"Age":25,"Area Income":65791.17},{"ID":484,"Age":30,"Area Income":34191.13},{"ID":485,"Age":37,"Area Income":51315.38},{"ID":486,"Age":35,"Area Income":62790.96},{"ID":487,"Age":40,"Area Income":66291.67},{"ID":488,"Age":30,"Area Income":68030.18},{"ID":489,"Age":48,"Area Income":43974.49},{"ID":490,"Age":31,"Area Income":49457.48},{"ID":491,"Age":40,"Area Income":33987.27},{"ID":492,"Age":33,"Area Income":28210.03},{"ID":493,"Age":30,"Area Income":75535.14},{"ID":494,"Age":28,"Area Income":49158.5},{"ID":495,"Age":30,"Area Income":39809.69},{"ID":496,"Age":35,"Area Income":65826.53},{"ID":497,"Age":29,"Area Income":61172.07},{"ID":498,"Age":39,"Area Income":42898.21},{"ID":499,"Age":27,"Area Income":68333.01},{"ID":500,"Age":37,"Area Income":70232.95},{"ID":501,"Age":46,"Area Income":63102.19},{"ID":502,"Age":37,"Area Income":51847.26},{"ID":503,"Age":26,"Area Income":63580.22},{"ID":504,"Age":37,"Area Income":47575.44},{"ID":505,"Age":49,"Area Income":39031.89},{"ID":506,"Age":42,"Area Income":70505.06},{"ID":507,"Age":31,"Area Income":62161.26},{"ID":508,"Age":41,"Area Income":61068.26},{"ID":509,"Age":58,"Area Income":49090.51},{"ID":510,"Age":33,"Area Income":62330.75},{"ID":511,"Age":30,"Area Income":18819.34},{"ID":512,"Age":26,"Area Income":62053.37},{"ID":513,"Age":33,"Area Income":61922.06},{"ID":514,"Age":44,"Area Income":49525.37},{"ID":515,"Age":41,"Area Income":53412.32},{"ID":516,"Age":37,"Area Income":56681.65},{"ID":517,"Age":32,"Area Income":43299.63},{"ID":518,"Age":34,"Area Income":47997.75},{"ID":519,"Age":55,"Area Income":39131.53},{"ID":520,"Age":40,"Area Income":46033.73},{"ID":521,"Age":42,"Area Income":65856.74},{"ID":522,"Age":29,"Area Income":54787.37},{"ID":523,"Age":32,"Area Income":69562.46},{"ID":524,"Age":43,"Area Income":68447.17},{"ID":525,"Age":32,"Area Income":62772.42},{"ID":526,"Age":41,"Area Income":78092.95},{"ID":527,"Age":39,"Area Income":63649.04},{"ID":528,"Age":21,"Area Income":60637.62},{"ID":529,"Age":52,"Area Income":27241.11},{"ID":530,"Age":34,"Area Income":42760.22},{"ID":531,"Age":49,"Area Income":59457.52},{"ID":532,"Age":42,"Area Income":42907.89},{"ID":533,"Age":51,"Area Income":46132.18},{"ID":534,"Age":39,"Area Income":46964.11},{"ID":535,"Age":30,"Area Income":70377.23},{"ID":536,"Age":32,"Area Income":70012.83},{"ID":537,"Age":23,"Area Income":56457.01},{"ID":538,"Age":26,"Area Income":67279.06},{"ID":539,"Age":35,"Area Income":54773.99},{"ID":540,"Age":34,"Area Income":70783.94},{"ID":541,"Age":36,"Area Income":70510.59},{"ID":542,"Age":39,"Area Income":64021.55},{"ID":543,"Age":33,"Area Income":72042.85},{"ID":544,"Age":38,"Area Income":36037.33},{"ID":545,"Age":29,"Area Income":67526.92},{"ID":546,"Age":55,"Area Income":55121.65},{"ID":547,"Age":28,"Area Income":63497.62},{"ID":548,"Age":39,"Area Income":60879.48},{"ID":549,"Age":33,"Area Income":61467.33},{"ID":550,"Age":35,"Area Income":70495.64},{"ID":551,"Age":36,"Area Income":71222.4},{"ID":552,"Age":31,"Area Income":64698.58},{"ID":553,"Age":58,"Area Income":32252.38},{"ID":554,"Age":35,"Area Income":55316.97},{"ID":555,"Age":33,"Area Income":47447.89},{"ID":556,"Age":37,"Area Income":73474.82},{"ID":557,"Age":49,"Area Income":53549.94},{"ID":558,"Age":28,"Area Income":58576.12},{"ID":559,"Age":26,"Area Income":63373.7},{"ID":560,"Age":31,"Area Income":60283.47},{"ID":561,"Age":44,"Area Income":37345.34},{"ID":562,"Age":41,"Area Income":34886.01},{"ID":563,"Age":44,"Area Income":67511.86},{"ID":564,"Age":37,"Area Income":77988.71},{"ID":565,"Age":36,"Area Income":63001.03},{"ID":566,"Age":26,"Area Income":61747.98},{"ID":567,"Age":42,"Area Income":48467.68},{"ID":568,"Age":30,"Area Income":55130.96},{"ID":569,"Age":42,"Area Income":79484.8},{"ID":570,"Age":37,"Area Income":67307.43},{"ID":571,"Age":40,"Area Income":27964.6},{"ID":572,"Age":33,"Area Income":66431.87},{"ID":573,"Age":35,"Area Income":63551.67},{"ID":574,"Age":23,"Area Income":40135.06},{"ID":575,"Age":45,"Area Income":49101.67},{"ID":576,"Age":54,"Area Income":53188.69},{"ID":577,"Age":39,"Area Income":49742.83},{"ID":578,"Age":36,"Area Income":63394.41},{"ID":579,"Age":23,"Area Income":64433.99},{"ID":580,"Age":38,"Area Income":73884.48},{"ID":581,"Age":46,"Area Income":36424.94},{"ID":582,"Age":36,"Area Income":28275.48},{"ID":583,"Age":27,"Area Income":48098.86},{"ID":584,"Age":33,"Area Income":68448.94},{"ID":585,"Age":25,"Area Income":66429.84},{"ID":586,"Age":46,"Area Income":41768.13},{"ID":587,"Age":38,"Area Income":57844.96},{"ID":588,"Age":45,"Area Income":35684.82},{"ID":589,"Age":32,"Area Income":62792.43},{"ID":590,"Age":28,"Area Income":51171.23},{"ID":591,"Age":25,"Area Income":58847.07},{"ID":592,"Age":42,"Area Income":57739.03},{"ID":593,"Age":25,"Area Income":64631.22},{"ID":594,"Age":24,"Area Income":50337.93},{"ID":595,"Age":38,"Area Income":67781.31},{"ID":596,"Age":36,"Area Income":68863.95},{"ID":597,"Age":27,"Area Income":55901.12},{"ID":598,"Age":37,"Area Income":64775.1},{"ID":599,"Age":36,"Area Income":67686.16},{"ID":600,"Age":48,"Area Income":57777.11},{"ID":601,"Age":48,"Area Income":46868.53},{"ID":602,"Age":50,"Area Income":40926.93},{"ID":603,"Age":40,"Area Income":22205.74},{"ID":604,"Age":24,"Area Income":58920.44},{"ID":605,"Age":35,"Area Income":63006.14},{"ID":606,"Age":51,"Area Income":24316.61},{"ID":607,"Age":26,"Area Income":68348.99},{"ID":608,"Age":30,"Area Income":66263.37},{"ID":609,"Age":40,"Area Income":63493.6},{"ID":610,"Age":30,"Area Income":56984.09},{"ID":611,"Age":37,"Area Income":51691.55},{"ID":612,"Age":31,"Area Income":49911.25},{"ID":613,"Age":31,"Area Income":33502.57},{"ID":614,"Age":31,"Area Income":65834.97},{"ID":615,"Age":31,"Area Income":66176.97},{"ID":616,"Age":53,"Area Income":51463.17},{"ID":617,"Age":41,"Area Income":41059.64},{"ID":618,"Age":38,"Area Income":61428.18},{"ID":619,"Age":39,"Area Income":51593.46},{"ID":620,"Age":24,"Area Income":57518.73},{"ID":621,"Age":24,"Area Income":52656.13},{"ID":622,"Age":31,"Area Income":52178.98},{"ID":623,"Age":50,"Area Income":46239.14},{"ID":624,"Age":35,"Area Income":48918.55},{"ID":625,"Age":27,"Area Income":65227.79},{"ID":626,"Age":23,"Area Income":55002.05},{"ID":627,"Age":27,"Area Income":52261.73},{"ID":628,"Age":49,"Area Income":59448.44},{"ID":629,"Age":39,"Area Income":47314.45},{"ID":630,"Age":26,"Area Income":55411.06},{"ID":631,"Age":29,"Area Income":66504.16},{"ID":632,"Age":36,"Area Income":47169.14},{"ID":633,"Age":31,"Area Income":70889.68},{"ID":634,"Age":37,"Area Income":55358.88},{"ID":635,"Age":55,"Area Income":56242.7},{"ID":636,"Age":51,"Area Income":45522.44},{"ID":637,"Age":49,"Area Income":46931.03},{"ID":638,"Age":40,"Area Income":55499.69},{"ID":639,"Age":41,"Area Income":75805.12},{"ID":640,"Age":23,"Area Income":40345.49},{"ID":641,"Age":45,"Area Income":15598.29},{"ID":642,"Age":28,"Area Income":33239.2},{"ID":643,"Age":36,"Area Income":68033.54},{"ID":644,"Age":22,"Area Income":38427.66},{"ID":645,"Age":46,"Area Income":53185.34},{"ID":646,"Age":28,"Area Income":39723.97},{"ID":647,"Age":41,"Area Income":43386.07},{"ID":648,"Age":28,"Area Income":53922.43},{"ID":649,"Age":27,"Area Income":71881.84},{"ID":650,"Age":29,"Area Income":47139.21},{"ID":651,"Age":38,"Area Income":68877.02},{"ID":652,"Age":33,"Area Income":65186.58},{"ID":653,"Age":32,"Area Income":55424.24},{"ID":654,"Age":46,"Area Income":46500.11},{"ID":655,"Age":26,"Area Income":58820.16},{"ID":656,"Age":43,"Area Income":28495.21},{"ID":657,"Age":31,"Area Income":61840.26},{"ID":658,"Age":46,"Area Income":37908.29},{"ID":659,"Age":39,"Area Income":69805.7},{"ID":660,"Age":26,"Area Income":60315.19},{"ID":661,"Age":49,"Area Income":67323},{"ID":662,"Age":26,"Area Income":50055.33},{"ID":663,"Age":50,"Area Income":43573.66},{"ID":664,"Age":55,"Area Income":28186.65},{"ID":665,"Age":33,"Area Income":66412.04},{"ID":666,"Age":32,"Area Income":15879.1},{"ID":667,"Age":29,"Area Income":63965.16},{"ID":668,"Age":31,"Area Income":58342.63},{"ID":669,"Age":31,"Area Income":33147.19},{"ID":670,"Age":33,"Area Income":65899.68},{"ID":671,"Age":26,"Area Income":64188.5},{"ID":672,"Age":61,"Area Income":58966.22},{"ID":673,"Age":33,"Area Income":44078.24},{"ID":674,"Age":55,"Area Income":60968.62},{"ID":675,"Age":28,"Area Income":65620.25},{"ID":676,"Age":38,"Area Income":65496.78},{"ID":677,"Age":29,"Area Income":52462.04},{"ID":678,"Age":38,"Area Income":70582.55},{"ID":679,"Age":34,"Area Income":51816.27},{"ID":680,"Age":46,"Area Income":23410.75},{"ID":681,"Age":26,"Area Income":62729.4},{"ID":682,"Age":28,"Area Income":48867.67},{"ID":683,"Age":36,"Area Income":50971.73},{"ID":684,"Age":28,"Area Income":67990.84},{"ID":685,"Age":34,"Area Income":43241.19},{"ID":686,"Age":27,"Area Income":60082.66},{"ID":687,"Age":37,"Area Income":65180.97},{"ID":688,"Age":28,"Area Income":67301.39},{"ID":689,"Age":36,"Area Income":70701.31},{"ID":690,"Age":28,"Area Income":60997.84},{"ID":691,"Age":33,"Area Income":60805.93},{"ID":692,"Age":37,"Area Income":50711.68},{"ID":693,"Age":47,"Area Income":14548.06},{"ID":694,"Age":29,"Area Income":41335.84},{"ID":695,"Age":33,"Area Income":76480.16},{"ID":696,"Age":38,"Area Income":67132.46},{"ID":697,"Age":54,"Area Income":52581.16},{"ID":698,"Age":25,"Area Income":55195.61},{"ID":699,"Age":28,"Area Income":48679.54},{"ID":700,"Age":29,"Area Income":63109.74},{"ID":701,"Age":19,"Area Income":44490.09},{"ID":702,"Age":54,"Area Income":57667.99},{"ID":703,"Age":30,"Area Income":51824.01},{"ID":704,"Age":28,"Area Income":66198.66},{"ID":705,"Age":40,"Area Income":73174.19},{"ID":706,"Age":26,"Area Income":56593.8},{"ID":707,"Age":23,"Area Income":31072.44},{"ID":708,"Age":41,"Area Income":66773.83},{"ID":709,"Age":48,"Area Income":72553.94},{"ID":710,"Age":57,"Area Income":43708.88},{"ID":711,"Age":43,"Area Income":48453.55},{"ID":712,"Age":31,"Area Income":73413.87},{"ID":713,"Age":35,"Area Income":58114.3},{"ID":714,"Age":53,"Area Income":45465.25},{"ID":715,"Age":21,"Area Income":50147.72},{"ID":716,"Age":38,"Area Income":61004.51},{"ID":717,"Age":35,"Area Income":53898.89},{"ID":718,"Age":29,"Area Income":59797.64},{"ID":719,"Age":51,"Area Income":74623.27},{"ID":720,"Age":45,"Area Income":58677.69},{"ID":721,"Age":34,"Area Income":62109.8},{"ID":722,"Age":36,"Area Income":60583.02},{"ID":723,"Age":43,"Area Income":65576.05},{"ID":724,"Age":40,"Area Income":73882.91},{"ID":725,"Age":25,"Area Income":50468.36},{"ID":726,"Age":27,"Area Income":51409.45},{"ID":727,"Age":24,"Area Income":60514.05},{"ID":728,"Age":30,"Area Income":57195.96},{"ID":729,"Age":34,"Area Income":52802.58},{"ID":730,"Age":28,"Area Income":56570.06},{"ID":731,"Age":19,"Area Income":51049.47},{"ID":732,"Age":35,"Area Income":66629.61},{"ID":733,"Age":41,"Area Income":70185.06},{"ID":734,"Age":41,"Area Income":43111.41},{"ID":735,"Age":26,"Area Income":56435.6},{"ID":736,"Age":29,"Area Income":53223.58},{"ID":737,"Age":28,"Area Income":57179.91},{"ID":738,"Age":52,"Area Income":41521.28},{"ID":739,"Age":43,"Area Income":73538.09},{"ID":740,"Age":30,"Area Income":63664.32},{"ID":741,"Age":38,"Area Income":61757.12},{"ID":742,"Age":28,"Area Income":71727.51},{"ID":743,"Age":29,"Area Income":72203.96},{"ID":744,"Age":37,"Area Income":50671.6},{"ID":745,"Age":29,"Area Income":47510.42},{"ID":746,"Age":50,"Area Income":62466.1},{"ID":747,"Age":29,"Area Income":59683.16},{"ID":748,"Age":32,"Area Income":41097.17},{"ID":749,"Age":58,"Area Income":39799.73},{"ID":750,"Age":42,"Area Income":76984.21},{"ID":751,"Age":59,"Area Income":57877.15},{"ID":752,"Age":31,"Area Income":59047.91},{"ID":753,"Age":28,"Area Income":72154.68},{"ID":754,"Age":31,"Area Income":65704.79},{"ID":755,"Age":36,"Area Income":72948.76},{"ID":756,"Age":34,"Area Income":73941.91},{"ID":757,"Age":37,"Area Income":57887.64},{"ID":758,"Age":35,"Area Income":62463.7},{"ID":759,"Age":29,"Area Income":42838.29},{"ID":760,"Age":32,"Area Income":43778.88},{"ID":761,"Age":40,"Area Income":71157.05},{"ID":762,"Age":31,"Area Income":74159.69},{"ID":763,"Age":54,"Area Income":50333.72},{"ID":764,"Age":25,"Area Income":33293.78},{"ID":765,"Age":51,"Area Income":38641.2},{"ID":766,"Age":33,"Area Income":49822.78},{"ID":767,"Age":29,"Area Income":63891.29},{"ID":768,"Age":42,"Area Income":43881.73},{"ID":769,"Age":41,"Area Income":13996.5},{"ID":770,"Age":27,"Area Income":48761.14},{"ID":771,"Age":30,"Area Income":69758.31},{"ID":772,"Age":19,"Area Income":52530.1},{"ID":773,"Age":40,"Area Income":58363.12},{"ID":774,"Age":50,"Area Income":60575.99},{"ID":775,"Age":45,"Area Income":48206.04},{"ID":776,"Age":54,"Area Income":31523.09},{"ID":777,"Age":26,"Area Income":66187.58},{"ID":778,"Age":30,"Area Income":69438.04},{"ID":779,"Age":44,"Area Income":14775.5},{"ID":780,"Age":35,"Area Income":68016.9},{"ID":781,"Age":41,"Area Income":78520.99},{"ID":782,"Age":36,"Area Income":31998.72},{"ID":783,"Age":29,"Area Income":56909.3},{"ID":784,"Age":29,"Area Income":61161.29},{"ID":785,"Age":39,"Area Income":52340.1},{"ID":786,"Age":40,"Area Income":47338.94},{"ID":787,"Age":22,"Area Income":50950.24},{"ID":788,"Age":33,"Area Income":77143.61},{"ID":789,"Age":29,"Area Income":57032.36},{"ID":790,"Age":33,"Area Income":48554.45},{"ID":791,"Age":31,"Area Income":39552.49},{"ID":792,"Age":47,"Area Income":36884.23},{"ID":793,"Age":26,"Area Income":68783.45},{"ID":794,"Age":32,"Area Income":51119.93},{"ID":795,"Age":49,"Area Income":44304.13},{"ID":796,"Age":29,"Area Income":69718.19},{"ID":797,"Age":27,"Area Income":63429.18},{"ID":798,"Age":34,"Area Income":65756.36},{"ID":799,"Age":46,"Area Income":77871.75},{"ID":800,"Age":24,"Area Income":47258.59},{"ID":801,"Age":29,"Area Income":55984.89},{"ID":802,"Age":34,"Area Income":44275.13},{"ID":803,"Age":50,"Area Income":25767.16},{"ID":804,"Age":49,"Area Income":37605.11},{"ID":805,"Age":41,"Area Income":25739.09},{"ID":806,"Age":28,"Area Income":60188.38},{"ID":807,"Age":43,"Area Income":67682.32},{"ID":808,"Age":44,"Area Income":44307.18},{"ID":809,"Age":35,"Area Income":25371.52},{"ID":810,"Age":43,"Area Income":23942.61},{"ID":811,"Age":29,"Area Income":50666.5},{"ID":812,"Age":30,"Area Income":50356.06},{"ID":813,"Age":32,"Area Income":63936.5},{"ID":814,"Age":28,"Area Income":69874.18},{"ID":815,"Age":34,"Area Income":50038.65},{"ID":816,"Age":39,"Area Income":67866.95},{"ID":817,"Age":48,"Area Income":54645.2},{"ID":818,"Age":23,"Area Income":46780.09},{"ID":819,"Age":34,"Area Income":67432.49},{"ID":820,"Age":39,"Area Income":73392.28},{"ID":821,"Age":38,"Area Income":47682.28},{"ID":822,"Age":31,"Area Income":56735.83},{"ID":823,"Age":30,"Area Income":51013.37},{"ID":824,"Age":32,"Area Income":69481.85},{"ID":825,"Age":28,"Area Income":67033.34},{"ID":826,"Age":36,"Area Income":68717},{"ID":827,"Age":31,"Area Income":59340.99},{"ID":828,"Age":45,"Area Income":47968.32},{"ID":829,"Age":35,"Area Income":48758.92},{"ID":830,"Age":49,"Area Income":61230.03},{"ID":831,"Age":30,"Area Income":54755.71},{"ID":832,"Age":34,"Area Income":54324.73},{"ID":833,"Age":42,"Area Income":52177.4},{"ID":834,"Age":33,"Area Income":51163.14},{"ID":835,"Age":27,"Area Income":66861.67},{"ID":836,"Age":34,"Area Income":63107.88},{"ID":837,"Age":46,"Area Income":49206.4},{"ID":838,"Age":49,"Area Income":55942.04},{"ID":839,"Age":40,"Area Income":33601.84},{"ID":840,"Age":46,"Area Income":48867.36},{"ID":841,"Age":40,"Area Income":56683.32},{"ID":842,"Age":45,"Area Income":38260.89},{"ID":843,"Age":23,"Area Income":54106.21},{"ID":844,"Age":38,"Area Income":71055.22},{"ID":845,"Age":37,"Area Income":46403.18},{"ID":846,"Age":42,"Area Income":61690.93},{"ID":847,"Age":37,"Area Income":26130.93},{"ID":848,"Age":36,"Area Income":58638.75},{"ID":849,"Age":32,"Area Income":47357.39},{"ID":850,"Age":52,"Area Income":50086.17},{"ID":851,"Age":33,"Area Income":51772.58},{"ID":852,"Age":35,"Area Income":47638.3},{"ID":853,"Age":45,"Area Income":38987.42},{"ID":854,"Age":26,"Area Income":51363.16},{"ID":855,"Age":34,"Area Income":35764.49},{"ID":856,"Age":24,"Area Income":62939.5},{"ID":857,"Age":30,"Area Income":58776.67},{"ID":858,"Age":25,"Area Income":59106.12},{"ID":859,"Age":51,"Area Income":50457.01},{"ID":860,"Age":43,"Area Income":54251.78},{"ID":861,"Age":45,"Area Income":51920.49},{"ID":862,"Age":29,"Area Income":70324.8},{"ID":863,"Age":25,"Area Income":52416.18},{"ID":864,"Age":39,"Area Income":66217.31},{"ID":865,"Age":50,"Area Income":60938.73},{"ID":866,"Age":33,"Area Income":40243.82},{"ID":867,"Age":32,"Area Income":60151.77},{"ID":868,"Age":40,"Area Income":45945.88},{"ID":869,"Age":25,"Area Income":63430.33},{"ID":870,"Age":36,"Area Income":65882.81},{"ID":871,"Age":27,"Area Income":64410.8},{"ID":872,"Age":27,"Area Income":55677.12},{"ID":873,"Age":33,"Area Income":75560.65},{"ID":874,"Age":32,"Area Income":61067.58},{"ID":875,"Age":34,"Area Income":72330.57},{"ID":876,"Age":29,"Area Income":32549.95},{"ID":877,"Age":44,"Area Income":51257.26},{"ID":878,"Age":34,"Area Income":77220.42},{"ID":879,"Age":43,"Area Income":52520.75},{"ID":880,"Age":22,"Area Income":59422.47},{"ID":881,"Age":33,"Area Income":22456.04},{"ID":882,"Age":31,"Area Income":58443.99},{"ID":883,"Age":29,"Area Income":50820.74},{"ID":884,"Age":42,"Area Income":67575.12},{"ID":885,"Age":39,"Area Income":66522.79},{"ID":886,"Age":45,"Area Income":34903.67},{"ID":887,"Age":53,"Area Income":43073.78},{"ID":888,"Age":44,"Area Income":57594.7},{"ID":889,"Age":31,"Area Income":66027.31},{"ID":890,"Age":36,"Area Income":53012.94},{"ID":891,"Age":31,"Area Income":61117.5},{"ID":892,"Age":20,"Area Income":52563.22},{"ID":893,"Age":40,"Area Income":65773.49},{"ID":894,"Age":25,"Area Income":50506.44},{"ID":895,"Age":36,"Area Income":66262.59},{"ID":896,"Age":26,"Area Income":35521.88},{"ID":897,"Age":32,"Area Income":62430.55},{"ID":898,"Age":41,"Area Income":49597.08},{"ID":899,"Age":37,"Area Income":42078.89},{"ID":900,"Age":45,"Area Income":46197.59},{"ID":901,"Age":51,"Area Income":49957},{"ID":902,"Age":38,"Area Income":24078.93},{"ID":903,"Age":43,"Area Income":53647.81},{"ID":904,"Age":30,"Area Income":61039.13},{"ID":905,"Age":26,"Area Income":46974.15},{"ID":906,"Age":27,"Area Income":53042.51},{"ID":907,"Age":50,"Area Income":48826.14},{"ID":908,"Age":31,"Area Income":58287.86},{"ID":909,"Age":50,"Area Income":21773.22},{"ID":910,"Age":24,"Area Income":52252.91},{"ID":911,"Age":52,"Area Income":27073.27},{"ID":912,"Age":47,"Area Income":50628.31},{"ID":913,"Age":42,"Area Income":36913.51},{"ID":914,"Age":37,"Area Income":61009.1},{"ID":915,"Age":39,"Area Income":53041.77},{"ID":916,"Age":34,"Area Income":40182.84},{"ID":917,"Age":42,"Area Income":59419.78},{"ID":918,"Age":31,"Area Income":58235.21},{"ID":919,"Age":32,"Area Income":68324.48},{"ID":920,"Age":25,"Area Income":69646.35},{"ID":921,"Age":34,"Area Income":54045.39},{"ID":922,"Age":37,"Area Income":57806.03},{"ID":923,"Age":49,"Area Income":53336.76},{"ID":924,"Age":56,"Area Income":50491.45},{"ID":925,"Age":51,"Area Income":71455.62},{"ID":926,"Age":45,"Area Income":43241.88},{"ID":927,"Age":22,"Area Income":58953.01},{"ID":928,"Age":38,"Area Income":36834.04},{"ID":929,"Age":29,"Area Income":66345.1},{"ID":930,"Age":45,"Area Income":38645.4},{"ID":931,"Age":36,"Area Income":60803},{"ID":932,"Age":34,"Area Income":33553.9},{"ID":933,"Age":38,"Area Income":63071.34},{"ID":934,"Age":34,"Area Income":46737.34},{"ID":935,"Age":33,"Area Income":55368.67},{"ID":936,"Age":36,"Area Income":68305.91},{"ID":937,"Age":45,"Area Income":39211.49},{"ID":938,"Age":48,"Area Income":65956.71},{"ID":939,"Age":38,"Area Income":40159.2},{"ID":940,"Age":19,"Area Income":40478.83},{"ID":941,"Age":46,"Area Income":40468.53},{"ID":942,"Age":51,"Area Income":66980.27},{"ID":943,"Age":39,"Area Income":34942.26},{"ID":944,"Age":32,"Area Income":48335.2},{"ID":945,"Age":30,"Area Income":42251.59},{"ID":946,"Age":36,"Area Income":57330.43},{"ID":947,"Age":34,"Area Income":75769.82},{"ID":948,"Age":31,"Area Income":51812.71},{"ID":949,"Age":30,"Area Income":75265.96},{"ID":950,"Age":50,"Area Income":69868.48},{"ID":951,"Age":43,"Area Income":72802.42},{"ID":952,"Age":27,"Area Income":39193.45},{"ID":953,"Age":36,"Area Income":18368.57},{"ID":954,"Age":29,"Area Income":56129.89},{"ID":955,"Age":31,"Area Income":58996.56},{"ID":956,"Age":44,"Area Income":41547.62},{"ID":957,"Age":36,"Area Income":59240.24},{"ID":958,"Age":28,"Area Income":56725.47},{"ID":959,"Age":29,"Area Income":55764.43},{"ID":960,"Age":37,"Area Income":64235.51},{"ID":961,"Age":28,"Area Income":39939.39},{"ID":962,"Age":26,"Area Income":63319.99},{"ID":963,"Age":21,"Area Income":54725.87},{"ID":964,"Age":42,"Area Income":69775.75},{"ID":965,"Age":24,"Area Income":57545.56},{"ID":966,"Age":50,"Area Income":47051.02},{"ID":967,"Age":52,"Area Income":51600.47},{"ID":968,"Age":25,"Area Income":68357.96},{"ID":969,"Age":38,"Area Income":35349.26},{"ID":970,"Age":27,"Area Income":69784.85},{"ID":971,"Age":29,"Area Income":50760.23},{"ID":972,"Age":48,"Area Income":34418.09},{"ID":973,"Age":50,"Area Income":20592.99},{"ID":974,"Age":28,"Area Income":63528.8},{"ID":975,"Age":40,"Area Income":44217.68},{"ID":976,"Age":48,"Area Income":47929.83},{"ID":977,"Age":45,"Area Income":46024.29},{"ID":978,"Age":31,"Area Income":51900.03},{"ID":979,"Age":30,"Area Income":72188.9},{"ID":980,"Age":31,"Area Income":56974.51},{"ID":981,"Age":57,"Area Income":25682.65},{"ID":982,"Age":46,"Area Income":41884.64},{"ID":983,"Age":38,"Area Income":72196.29},{"ID":984,"Age":32,"Area Income":54429.17},{"ID":985,"Age":31,"Area Income":58037.66},{"ID":986,"Age":44,"Area Income":64011.26},{"ID":987,"Age":28,"Area Income":59967.19},{"ID":988,"Age":43,"Area Income":43155.19},{"ID":989,"Age":48,"Area Income":51501.38},{"ID":990,"Age":31,"Area Income":55187.85},{"ID":991,"Age":44,"Area Income":33813.08},{"ID":992,"Age":38,"Area Income":36497.22},{"ID":993,"Age":40,"Area Income":66193.81},{"ID":994,"Age":27,"Area Income":66200.96},{"ID":995,"Age":28,"Area Income":63126.96},{"ID":996,"Age":30,"Area Income":71384.57},{"ID":997,"Age":45,"Area Income":67782.17},{"ID":998,"Age":51,"Area Income":42415.72},{"ID":999,"Age":73,"Area Income":41920.79},{"ID":1000,"Age":68,"Area Income":29875.8},{"ID":1001,"Age":65,"Area Income":37720.13778},{"ID":1002,"Age":66,"Area Income":59125.95533},{"ID":1003,"Age":74,"Area Income":46917.31448},{"ID":1004,"Age":68,"Area Income":35970.03067},{"ID":1005,"Age":66,"Area Income":31102.02145},{"ID":1006,"Age":68,"Area Income":38562.99401},{"ID":1007,"Age":80,"Area Income":34414.31533},{"ID":1008,"Age":75,"Area Income":40639.34215},{"ID":1009,"Age":69,"Area Income":58440.09561},{"ID":1010,"Age":79,"Area Income":52603.52899},{"ID":1011,"Age":73,"Area Income":40177.72256},{"ID":1012,"Age":72,"Area Income":37209.90123},{"ID":1013,"Age":80,"Area Income":50734.97406},{"ID":1014,"Age":71,"Area Income":40290.91738},{"ID":1015,"Age":69,"Area Income":39821.73251},{"ID":1016,"Age":69,"Area Income":32171.95845},{"ID":1017,"Age":68,"Area Income":43493.69282},{"ID":1018,"Age":70,"Area Income":42988.0972},{"ID":1019,"Age":68,"Area Income":36957.19104},{"ID":1020,"Age":67,"Area Income":44457.97292},{"ID":1021,"Age":79,"Area Income":58798.02839},{"ID":1022,"Age":69,"Area Income":53632.74106},{"ID":1023,"Age":65,"Area Income":55067.27578},{"ID":1024,"Age":70,"Area Income":52157.21742},{"ID":1025,"Age":78,"Area Income":31562.81823},{"ID":1026,"Age":78,"Area Income":59612.3682},{"ID":1027,"Age":68,"Area Income":46849.84842},{"ID":1028,"Age":78,"Area Income":42795.90529},{"ID":1029,"Age":80,"Area Income":32293.67153},{"ID":1030,"Age":79,"Area Income":36071.11376},{"ID":1031,"Age":77,"Area Income":42227.49767},{"ID":1032,"Age":65,"Area Income":36439.28213},{"ID":1033,"Age":72,"Area Income":49218.60798},{"ID":1034,"Age":80,"Area Income":30389.03285},{"ID":1035,"Age":75,"Area Income":35857.96166},{"ID":1036,"Age":68,"Area Income":56972.06927},{"ID":1037,"Age":73,"Area Income":55536.60579},{"ID":1038,"Age":65,"Area Income":45270.53023},{"ID":1039,"Age":79,"Area Income":52586.81511},{"ID":1040,"Age":72,"Area Income":39886.98303},{"ID":1041,"Age":71,"Area Income":40356.83155},{"ID":1042,"Age":74,"Area Income":54767.90369},{"ID":1043,"Age":76,"Area Income":57249.1162},{"ID":1044,"Age":76,"Area Income":43080.37354},{"ID":1045,"Age":69,"Area Income":47390.70981},{"ID":1046,"Age":70,"Area Income":33994.16752},{"ID":1047,"Age":77,"Area Income":41210.29141},{"ID":1048,"Age":67,"Area Income":35729.46207},{"ID":1049,"Age":80,"Area Income":52463.51218},{"ID":1050,"Age":78,"Area Income":50474.9507},{"ID":1051,"Age":67,"Area Income":44673.69725},{"ID":1052,"Age":78,"Area Income":39302.38505},{"ID":1053,"Age":78,"Area Income":33062.25074},{"ID":1054,"Age":76,"Area Income":35843.70751},{"ID":1055,"Age":68,"Area Income":35049.62799},{"ID":1056,"Age":73,"Area Income":52807.66917},{"ID":1057,"Age":67,"Area Income":52199.03529},{"ID":1058,"Age":72,"Area Income":32008.65637},{"ID":1059,"Age":77,"Area Income":56836.03847},{"ID":1060,"Age":69,"Area Income":55817.52314},{"ID":1061,"Age":68,"Area Income":34389.73028},{"ID":1062,"Age":78,"Area Income":39603.20951},{"ID":1063,"Age":70,"Area Income":49814.41321},{"ID":1064,"Age":67,"Area Income":33629.10171},{"ID":1065,"Age":68,"Area Income":44492.80744},{"ID":1066,"Age":70,"Area Income":53206.69587},{"ID":1067,"Age":78,"Area Income":56223.56635},{"ID":1068,"Age":69,"Area Income":44567.15776},{"ID":1069,"Age":71,"Area Income":35873.18101},{"ID":1070,"Age":78,"Area Income":30271.03733},{"ID":1071,"Age":69,"Area Income":43840.02247},{"ID":1072,"Age":67,"Area Income":41115.64747},{"ID":1073,"Age":68,"Area Income":34575.28977},{"ID":1074,"Age":74,"Area Income":45101.95575},{"ID":1075,"Age":67,"Area Income":48873.99686},{"ID":1076,"Age":70,"Area Income":37410.40206},{"ID":1077,"Age":69,"Area Income":56868.17457},{"ID":1078,"Age":80,"Area Income":47593.5151},{"ID":1079,"Age":75,"Area Income":42257.49132},{"ID":1080,"Age":67,"Area Income":55749.62008},{"ID":1081,"Age":77,"Area Income":49470.27331},{"ID":1082,"Age":70,"Area Income":47614.16079},{"ID":1083,"Age":74,"Area Income":54089.19194},{"ID":1084,"Age":71,"Area Income":47440.69162},{"ID":1085,"Age":79,"Area Income":35166.55435},{"ID":1086,"Age":68,"Area Income":34939.68869},{"ID":1087,"Age":77,"Area Income":53251.34721},{"ID":1088,"Age":68,"Area Income":32431.21569},{"ID":1089,"Age":80,"Area Income":56632.37684},{"ID":1090,"Age":69,"Area Income":46644.0955},{"ID":1091,"Age":67,"Area Income":56189.08563},{"ID":1092,"Age":80,"Area Income":58959.69329},{"ID":1093,"Age":68,"Area Income":56620.65369},{"ID":1094,"Age":78,"Area Income":57385.73495},{"ID":1095,"Age":76,"Area Income":54507.64975},{"ID":1096,"Age":71,"Area Income":51153.64163},{"ID":1097,"Age":71,"Area Income":41974.03575},{"ID":1098,"Age":72,"Area Income":46926.09003},{"ID":1099,"Age":80,"Area Income":31195.77637},{"ID":1100,"Age":75,"Area Income":50847.74449},{"ID":1101,"Age":67,"Area Income":42876.65119},{"ID":1102,"Age":79,"Area Income":54928.97754},{"ID":1103,"Age":72,"Area Income":44364.95273},{"ID":1104,"Age":79,"Area Income":36232.91209},{"ID":1105,"Age":74,"Area Income":35392.72792},{"ID":1106,"Age":73,"Area Income":58978.0657},{"ID":1107,"Age":74,"Area Income":49209.72145},{"ID":1108,"Age":74,"Area Income":58538.24761},{"ID":1109,"Age":68,"Area Income":30802.35232},{"ID":1110,"Age":72,"Area Income":46581.70458},{"ID":1111,"Age":78,"Area Income":44873.31706},{"ID":1112,"Age":69,"Area Income":35136.03835},{"ID":1113,"Age":72,"Area Income":36890.12246},{"ID":1114,"Age":67,"Area Income":46912.82893},{"ID":1115,"Age":77,"Area Income":41520.57897},{"ID":1116,"Age":78,"Area Income":50906.30684},{"ID":1117,"Age":79,"Area Income":43183.12157},{"ID":1118,"Age":65,"Area Income":59767.11915},{"ID":1119,"Age":78,"Area Income":31378.57218},{"ID":1120,"Age":66,"Area Income":52043.21276},{"ID":1121,"Age":72,"Area Income":55294.95482},{"ID":1122,"Age":69,"Area Income":41110.84467},{"ID":1123,"Age":79,"Area Income":49302.23346},{"ID":1124,"Age":77,"Area Income":39201.29925},{"ID":1125,"Age":72,"Area Income":48011.98513},{"ID":1126,"Age":79,"Area Income":40988.13748},{"ID":1127,"Age":77,"Area Income":53925.98196},{"ID":1128,"Age":71,"Area Income":38605.34908},{"ID":1129,"Age":67,"Area Income":48796.88116},{"ID":1130,"Age":69,"Area Income":32650.64172},{"ID":1131,"Age":80,"Area Income":39222.29851},{"ID":1132,"Age":75,"Area Income":38960.17562},{"ID":1133,"Age":75,"Area Income":46111.52179},{"ID":1134,"Age":76,"Area Income":57431.63413},{"ID":1135,"Age":77,"Area Income":56739.34865},{"ID":1136,"Age":74,"Area Income":56540.08434},{"ID":1137,"Age":65,"Area Income":30048.70473},{"ID":1138,"Age":71,"Area Income":43701.31096},{"ID":1139,"Age":76,"Area Income":39049.38345},{"ID":1140,"Age":77,"Area Income":51508.25658},{"ID":1141,"Age":75,"Area Income":52578.98347},{"ID":1142,"Age":74,"Area Income":54198.96289},{"ID":1143,"Age":70,"Area Income":52524.34308},{"ID":1144,"Age":78,"Area Income":44985.74727},{"ID":1145,"Age":76,"Area Income":52165.18445},{"ID":1146,"Age":79,"Area Income":34698.91397},{"ID":1147,"Age":77,"Area Income":54395.11072},{"ID":1148,"Age":72,"Area Income":48088.41147},{"ID":1149,"Age":65,"Area Income":34421.41255},{"ID":1150,"Age":67,"Area Income":59539.53912},{"ID":1151,"Age":66,"Area Income":48066.12259},{"ID":1152,"Age":65,"Area Income":48055.63127},{"ID":1153,"Age":66,"Area Income":41837.88789},{"ID":1154,"Age":68,"Area Income":33941.23356},{"ID":1155,"Age":66,"Area Income":47095.56602},{"ID":1156,"Age":75,"Area Income":43378.99017},{"ID":1157,"Age":78,"Area Income":58852.42088},{"ID":1158,"Age":71,"Area Income":40706.02119},{"ID":1159,"Age":65,"Area Income":50248.15963},{"ID":1160,"Age":70,"Area Income":35975.39754},{"ID":1161,"Age":78,"Area Income":53592.01704},{"ID":1162,"Age":80,"Area Income":37298.91034},{"ID":1163,"Age":80,"Area Income":55033.7786},{"ID":1164,"Age":79,"Area Income":35028.04897},{"ID":1165,"Age":65,"Area Income":50034.2707},{"ID":1166,"Age":80,"Area Income":54434.55588},{"ID":1167,"Age":65,"Area Income":55349.03701},{"ID":1168,"Age":70,"Area Income":38117.55232},{"ID":1169,"Age":70,"Area Income":40584.71168},{"ID":1170,"Age":76,"Area Income":42432.03965},{"ID":1171,"Age":67,"Area Income":30158.9013},{"ID":1172,"Age":68,"Area Income":40163.9183},{"ID":1173,"Age":76,"Area Income":49915.7642},{"ID":1174,"Age":69,"Area Income":43840.95426},{"ID":1175,"Age":69,"Area Income":35902.89217},{"ID":1176,"Age":79,"Area Income":31781.81588},{"ID":1177,"Age":65,"Area Income":49209.10666},{"ID":1178,"Age":65,"Area Income":46661.76429},{"ID":1179,"Age":74,"Area Income":44768.04988},{"ID":1180,"Age":78,"Area Income":34158.15387},{"ID":1181,"Age":74,"Area Income":50036.27532},{"ID":1182,"Age":79,"Area Income":44148.279},{"ID":1183,"Age":79,"Area Income":42917.63175},{"ID":1184,"Age":78,"Area Income":30333.4027},{"ID":1185,"Age":67,"Area Income":35403.6547},{"ID":1186,"Age":74,"Area Income":38221.24559},{"ID":1187,"Age":76,"Area Income":50725.38979},{"ID":1188,"Age":68,"Area Income":48369.3605},{"ID":1189,"Age":69,"Area Income":56105.86354},{"ID":1190,"Age":74,"Area Income":31188.83133},{"ID":1191,"Age":72,"Area Income":31863.77042},{"ID":1192,"Age":71,"Area Income":59485.07653},{"ID":1193,"Age":70,"Area Income":33956.6025},{"ID":1194,"Age":66,"Area Income":53052.36556},{"ID":1195,"Age":74,"Area Income":59462.61241},{"ID":1196,"Age":78,"Area Income":51152.33086},{"ID":1197,"Age":72,"Area Income":45835.84471},{"ID":1198,"Age":67,"Area Income":47317.30431},{"ID":1199,"Age":71,"Area Income":36523.12148},{"ID":1200,"Age":71,"Area Income":31573.69162},{"ID":1201,"Age":78,"Area Income":39379.11895},{"ID":1202,"Age":75,"Area Income":33511.29273},{"ID":1203,"Age":74,"Area Income":38565.99359},{"ID":1204,"Age":70,"Area Income":56616.43907},{"ID":1205,"Age":74,"Area Income":52440.25174},{"ID":1206,"Age":72,"Area Income":30114.31284},{"ID":1207,"Age":80,"Area Income":35651.77007},{"ID":1208,"Age":71,"Area Income":33840.87763},{"ID":1209,"Age":67,"Area Income":34305.01085},{"ID":1210,"Age":68,"Area Income":49292.05253},{"ID":1211,"Age":66,"Area Income":38026.78376},{"ID":1212,"Age":73,"Area Income":53667.20263},{"ID":1213,"Age":79,"Area Income":53043.54549},{"ID":1214,"Age":74,"Area Income":33283.83942},{"ID":1215,"Age":71,"Area Income":34032.68719},{"ID":1216,"Age":78,"Area Income":58644.61448},{"ID":1217,"Age":75,"Area Income":49879.86875},{"ID":1218,"Age":72,"Area Income":43541.752},{"ID":1219,"Age":74,"Area Income":32422.66227},{"ID":1220,"Age":77,"Area Income":44775.06844},{"ID":1221,"Age":70,"Area Income":57898.31598},{"ID":1222,"Age":80,"Area Income":39183.29448},{"ID":1223,"Age":69,"Area Income":34051.77288},{"ID":1224,"Age":74,"Area Income":39448.37686},{"ID":1225,"Age":68,"Area Income":45192.03958},{"ID":1226,"Age":68,"Area Income":36665.72139},{"ID":1227,"Age":79,"Area Income":32133.75372},{"ID":1228,"Age":70,"Area Income":50292.23806},{"ID":1229,"Age":68,"Area Income":51593.89455},{"ID":1230,"Age":65,"Area Income":35667.25455},{"ID":1231,"Age":79,"Area Income":41003.84876},{"ID":1232,"Age":66,"Area Income":34483.37135},{"ID":1233,"Age":65,"Area Income":40022.53026},{"ID":1234,"Age":80,"Area Income":42995.26506},{"ID":1235,"Age":73,"Area Income":40148.27138},{"ID":1236,"Age":78,"Area Income":42446.07138},{"ID":1237,"Age":68,"Area Income":47258.14947},{"ID":1238,"Age":78,"Area Income":54419.26291},{"ID":1239,"Age":66,"Area Income":43108.97977},{"ID":1240,"Age":80,"Area Income":36463.79766},{"ID":1241,"Age":69,"Area Income":54100.91446},{"ID":1242,"Age":80,"Area Income":52917.70113},{"ID":1243,"Age":67,"Area Income":40695.41866},{"ID":1244,"Age":78,"Area Income":36296.24445},{"ID":1245,"Age":74,"Area Income":39951.31621},{"ID":1246,"Age":68,"Area Income":41227.49553},{"ID":1247,"Age":79,"Area Income":34416.16319},{"ID":1248,"Age":78,"Area Income":40659.34306},{"ID":1249,"Age":77,"Area Income":32881.98108},{"ID":1250,"Age":71,"Area Income":44029.79583},{"ID":1251,"Age":80,"Area Income":55573.91397},{"ID":1252,"Age":66,"Area Income":30762.96583},{"ID":1253,"Age":73,"Area Income":55097.99334},{"ID":1254,"Age":77,"Area Income":58069.91149},{"ID":1255,"Age":70,"Area Income":44259.77328},{"ID":1256,"Age":78,"Area Income":40014.63513},{"ID":1257,"Age":70,"Area Income":55438.15706},{"ID":1258,"Age":71,"Area Income":46408.2049},{"ID":1259,"Age":76,"Area Income":47065.52201},{"ID":1260,"Age":78,"Area Income":42726.71432},{"ID":1261,"Age":72,"Area Income":52004.3996},{"ID":1262,"Age":74,"Area Income":36205.49117},{"ID":1263,"Age":77,"Area Income":38255.43867},{"ID":1264,"Age":65,"Area Income":37690.0548},{"ID":1265,"Age":72,"Area Income":33791.16233},{"ID":1266,"Age":69,"Area Income":56245.98813},{"ID":1267,"Age":65,"Area Income":31721.08186},{"ID":1268,"Age":75,"Area Income":39608.40711},{"ID":1269,"Age":77,"Area Income":46618.22235},{"ID":1270,"Age":67,"Area Income":48161.95022},{"ID":1271,"Age":73,"Area Income":41213.73906},{"ID":1272,"Age":65,"Area Income":44955.08503},{"ID":1273,"Age":67,"Area Income":36136.96225},{"ID":1274,"Age":67,"Area Income":59121.10353},{"ID":1275,"Age":73,"Area Income":49316.78108},{"ID":1276,"Age":65,"Area Income":39819.5567},{"ID":1277,"Age":67,"Area Income":38964.93623},{"ID":1278,"Age":71,"Area Income":46008.15816},{"ID":1279,"Age":79,"Area Income":52889.24584},{"ID":1280,"Age":75,"Area Income":37747.92158},{"ID":1281,"Age":67,"Area Income":32284.67407},{"ID":1282,"Age":78,"Area Income":55616.63674},{"ID":1283,"Age":74,"Area Income":50687.86384},{"ID":1284,"Age":71,"Area Income":45378.0506},{"ID":1285,"Age":76,"Area Income":40289.20658},{"ID":1286,"Age":74,"Area Income":37284.72836},{"ID":1287,"Age":73,"Area Income":52673.2652},{"ID":1288,"Age":79,"Area Income":43328.76389},{"ID":1289,"Age":76,"Area Income":31208.14757},{"ID":1290,"Age":71,"Area Income":53588.14414},{"ID":1291,"Age":78,"Area Income":43927.40881},{"ID":1292,"Age":77,"Area Income":39565.67393},{"ID":1293,"Age":79,"Area Income":54028.73305},{"ID":1294,"Age":72,"Area Income":48052.71644},{"ID":1295,"Age":71,"Area Income":35176.43523},{"ID":1296,"Age":67,"Area Income":40746.51015},{"ID":1297,"Age":78,"Area Income":40872.64228},{"ID":1298,"Age":68,"Area Income":53494.19326},{"ID":1299,"Age":76,"Area Income":32745.07026},{"ID":1300,"Age":79,"Area Income":54657.43369},{"ID":1301,"Age":75,"Area Income":57849.49133},{"ID":1302,"Age":76,"Area Income":40281.20572},{"ID":1303,"Age":74,"Area Income":58616.61619},{"ID":1304,"Age":74,"Area Income":37993.13255},{"ID":1305,"Age":69,"Area Income":54802.01378},{"ID":1306,"Age":71,"Area Income":30307.8501},{"ID":1307,"Age":66,"Area Income":51380.74298},{"ID":1308,"Age":70,"Area Income":58276.04772},{"ID":1309,"Age":66,"Area Income":58064.06522},{"ID":1310,"Age":74,"Area Income":59268.63148},{"ID":1311,"Age":76,"Area Income":59132.78148},{"ID":1312,"Age":71,"Area Income":52890.87831},{"ID":1313,"Age":79,"Area Income":38024.14599},{"ID":1314,"Age":70,"Area Income":53614.21149},{"ID":1315,"Age":72,"Area Income":53595.45267},{"ID":1316,"Age":77,"Area Income":55524.73251},{"ID":1317,"Age":79,"Area Income":41151.46858},{"ID":1318,"Age":79,"Area Income":51540.18005},{"ID":1319,"Age":70,"Area Income":59854.49676},{"ID":1320,"Age":69,"Area Income":32045.3611},{"ID":1321,"Age":66,"Area Income":46537.31188},{"ID":1322,"Age":69,"Area Income":35832.23801},{"ID":1323,"Age":78,"Area Income":47126.82148},{"ID":1324,"Age":79,"Area Income":45283.04532},{"ID":1325,"Age":74,"Area Income":41651.14839},{"ID":1326,"Age":71,"Area Income":30186.09843},{"ID":1327,"Age":65,"Area Income":36924.15351},{"ID":1328,"Age":66,"Area Income":38920.66615},{"ID":1329,"Age":73,"Area Income":42898.57391},{"ID":1330,"Age":79,"Area Income":30279.79121},{"ID":1331,"Age":68,"Area Income":42391.57162},{"ID":1332,"Age":76,"Area Income":55467.81586},{"ID":1333,"Age":77,"Area Income":56379.62478},{"ID":1334,"Age":78,"Area Income":37622.83709},{"ID":1335,"Age":66,"Area Income":33304.95631},{"ID":1336,"Age":69,"Area Income":33640.54621},{"ID":1337,"Age":66,"Area Income":30784.13985},{"ID":1338,"Age":72,"Area Income":56995.47761},{"ID":1339,"Age":66,"Area Income":56001.38339},{"ID":1340,"Age":69,"Area Income":36041.15114},{"ID":1341,"Age":65,"Area Income":46859.64457},{"ID":1342,"Age":67,"Area Income":32280.65161},{"ID":1343,"Age":74,"Area Income":38742.93318},{"ID":1344,"Age":65,"Area Income":46268.40006},{"ID":1345,"Age":65,"Area Income":42286.73325},{"ID":1346,"Age":80,"Area Income":56093.83973},{"ID":1347,"Age":80,"Area Income":35654.57934},{"ID":1348,"Age":74,"Area Income":38092.07771},{"ID":1349,"Age":78,"Area Income":39018.19291},{"ID":1350,"Age":74,"Area Income":35626.80846},{"ID":1351,"Age":75,"Area Income":49207.23184},{"ID":1352,"Age":71,"Area Income":57935.26322},{"ID":1353,"Age":72,"Area Income":49856.67883},{"ID":1354,"Age":67,"Area Income":58216.80521},{"ID":1355,"Age":65,"Area Income":37134.2681},{"ID":1356,"Age":77,"Area Income":57417.34146},{"ID":1357,"Age":69,"Area Income":46520.07557},{"ID":1358,"Age":72,"Area Income":46240.67719},{"ID":1359,"Age":76,"Area Income":32718.52392},{"ID":1360,"Age":78,"Area Income":52190.36983},{"ID":1361,"Age":74,"Area Income":57955.57598},{"ID":1362,"Age":67,"Area Income":58244.83549},{"ID":1363,"Age":77,"Area Income":59836.76539},{"ID":1364,"Age":72,"Area Income":37748.57271},{"ID":1365,"Age":74,"Area Income":53302.11856},{"ID":1366,"Age":69,"Area Income":32388.83925},{"ID":1367,"Age":80,"Area Income":39397.48164},{"ID":1368,"Age":74,"Area Income":39298.51632},{"ID":1369,"Age":73,"Area Income":32428.72668},{"ID":1370,"Age":71,"Area Income":57681.20456},{"ID":1371,"Age":71,"Area Income":38970.26696},{"ID":1372,"Age":74,"Area Income":37811.91345},{"ID":1373,"Age":71,"Area Income":48524.87833},{"ID":1374,"Age":79,"Area Income":30020.00351},{"ID":1375,"Age":68,"Area Income":37379.68639},{"ID":1376,"Age":65,"Area Income":55654.87524},{"ID":1377,"Age":69,"Area Income":53006.70279},{"ID":1378,"Age":66,"Area Income":56317.56863},{"ID":1379,"Age":79,"Area Income":31418.2983},{"ID":1380,"Age":70,"Area Income":45718.50982},{"ID":1381,"Age":69,"Area Income":46229.70236},{"ID":1382,"Age":70,"Area Income":43337.40811},{"ID":1383,"Age":71,"Area Income":46835.4411},{"ID":1384,"Age":76,"Area Income":58336.68747},{"ID":1385,"Age":68,"Area Income":35530.96784},{"ID":1386,"Age":67,"Area Income":30503.54704},{"ID":1387,"Age":78,"Area Income":37691.91515},{"ID":1388,"Age":80,"Area Income":44316.66294},{"ID":1389,"Age":72,"Area Income":51354.6803},{"ID":1390,"Age":70,"Area Income":53969.97137},{"ID":1391,"Age":67,"Area Income":47038.50848},{"ID":1392,"Age":71,"Area Income":33851.8156},{"ID":1393,"Age":67,"Area Income":54042.33091},{"ID":1394,"Age":75,"Area Income":40763.42489},{"ID":1395,"Age":68,"Area Income":47899.61806},{"ID":1396,"Age":76,"Area Income":50890.28392},{"ID":1397,"Age":76,"Area Income":51528.37313},{"ID":1398,"Age":72,"Area Income":52928.22925},{"ID":1399,"Age":79,"Area Income":56632.25187},{"ID":1400,"Age":67,"Area Income":41507.22234},{"ID":1401,"Age":74,"Area Income":35106.89397},{"ID":1402,"Age":69,"Area Income":57552.563},{"ID":1403,"Age":80,"Area Income":33808.51215},{"ID":1404,"Age":79,"Area Income":47885.83286},{"ID":1405,"Age":79,"Area Income":49067.99747},{"ID":1406,"Age":77,"Area Income":33663.24074},{"ID":1407,"Age":74,"Area Income":43174.44278},{"ID":1408,"Age":70,"Area Income":49848.92047},{"ID":1409,"Age":68,"Area Income":43313.44199},{"ID":1410,"Age":77,"Area Income":44254.19336},{"ID":1411,"Age":67,"Area Income":52379.51592},{"ID":1412,"Age":69,"Area Income":39259.28901},{"ID":1413,"Age":76,"Area Income":43830.75065},{"ID":1414,"Age":80,"Area Income":44480.4503},{"ID":1415,"Age":67,"Area Income":47860.03919},{"ID":1416,"Age":70,"Area Income":43858.49498},{"ID":1417,"Age":71,"Area Income":51963.08525},{"ID":1418,"Age":73,"Area Income":54347.52576},{"ID":1419,"Age":79,"Area Income":36792.57206},{"ID":1420,"Age":71,"Area Income":45892.0372},{"ID":1421,"Age":67,"Area Income":42797.13009},{"ID":1422,"Age":71,"Area Income":41536.30467},{"ID":1423,"Age":68,"Area Income":43926.27341},{"ID":1424,"Age":80,"Area Income":52321.27702},{"ID":1425,"Age":72,"Area Income":30139.05515},{"ID":1426,"Age":65,"Area Income":44992.82459},{"ID":1427,"Age":76,"Area Income":52409.19617},{"ID":1428,"Age":73,"Area Income":53230.22144},{"ID":1429,"Age":75,"Area Income":39668.62821},{"ID":1430,"Age":68,"Area Income":34417.05326},{"ID":1431,"Age":77,"Area Income":38331.14132},{"ID":1432,"Age":73,"Area Income":44626.52842},{"ID":1433,"Age":72,"Area Income":31276.10209},{"ID":1434,"Age":74,"Area Income":49732.41897},{"ID":1435,"Age":66,"Area Income":42568.5168},{"ID":1436,"Age":73,"Area Income":41632.99556},{"ID":1437,"Age":74,"Area Income":37888.81006},{"ID":1438,"Age":78,"Area Income":34865.57668},{"ID":1439,"Age":80,"Area Income":42088.1237},{"ID":1440,"Age":65,"Area Income":36454.12332},{"ID":1441,"Age":80,"Area Income":57749.32617},{"ID":1442,"Age":74,"Area Income":44135.44552},{"ID":1443,"Age":78,"Area Income":58247.43478},{"ID":1444,"Age":71,"Area Income":58745.28634},{"ID":1445,"Age":74,"Area Income":39295.40947},{"ID":1446,"Age":70,"Area Income":39491.56498},{"ID":1447,"Age":70,"Area Income":44204.9589},{"ID":1448,"Age":74,"Area Income":52560.562},{"ID":1449,"Age":75,"Area Income":41249.08267},{"ID":1450,"Age":67,"Area Income":40993.78571},{"ID":1451,"Age":72,"Area Income":45023.41337},{"ID":1452,"Age":69,"Area Income":58304.41065},{"ID":1453,"Age":72,"Area Income":57578.91332},{"ID":1454,"Age":66,"Area Income":39960.99743},{"ID":1455,"Age":75,"Area Income":58690.60151},{"ID":1456,"Age":74,"Area Income":49953.45824},{"ID":1457,"Age":70,"Area Income":54486.124},{"ID":1458,"Age":68,"Area Income":52484.58445},{"ID":1459,"Age":72,"Area Income":50471.78909},{"ID":1460,"Age":71,"Area Income":31260.78099},{"ID":1461,"Age":66,"Area Income":58524.73006},{"ID":1462,"Age":68,"Area Income":53632.51333},{"ID":1463,"Age":69,"Area Income":35333.1482},{"ID":1464,"Age":80,"Area Income":58361.15698},{"ID":1465,"Age":77,"Area Income":46716.06122},{"ID":1466,"Age":68,"Area Income":44117.08129},{"ID":1467,"Age":76,"Area Income":42777.60815},{"ID":1468,"Age":75,"Area Income":50054.62627},{"ID":1469,"Age":78,"Area Income":54693.63483},{"ID":1470,"Age":73,"Area Income":36798.06488},{"ID":1471,"Age":80,"Area Income":50804.74024},{"ID":1472,"Age":68,"Area Income":56670.1453},{"ID":1473,"Age":72,"Area Income":47057.26756},{"ID":1474,"Age":73,"Area Income":39208.55329},{"ID":1475,"Age":76,"Area Income":54790.83827},{"ID":1476,"Age":79,"Area Income":57377.9459},{"ID":1477,"Age":72,"Area Income":52572.05561},{"ID":1478,"Age":66,"Area Income":48251.52068},{"ID":1479,"Age":68,"Area Income":47148.15366},{"ID":1480,"Age":79,"Area Income":35200.73027},{"ID":1481,"Age":70,"Area Income":55940.49874},{"ID":1482,"Age":74,"Area Income":30768.03586},{"ID":1483,"Age":74,"Area Income":37458.1675},{"ID":1484,"Age":70,"Area Income":40855.42766},{"ID":1485,"Age":71,"Area Income":49932.92472},{"ID":1486,"Age":68,"Area Income":59448.81561},{"ID":1487,"Age":77,"Area Income":49343.17236},{"ID":1488,"Age":75,"Area Income":44701.66656},{"ID":1489,"Age":77,"Area Income":58394.60955},{"ID":1490,"Age":66,"Area Income":53893.25252},{"ID":1491,"Age":66,"Area Income":57354.36534},{"ID":1492,"Age":78,"Area Income":37453.26591},{"ID":1493,"Age":73,"Area Income":46930.45175},{"ID":1494,"Age":70,"Area Income":52978.94378},{"ID":1495,"Age":70,"Area Income":56553.70839},{"ID":1496,"Age":78,"Area Income":36814.00014},{"ID":1497,"Age":80,"Area Income":34205.57786},{"ID":1498,"Age":71,"Area Income":45164.39174},{"ID":1499,"Age":79,"Area Income":43156.52461},{"ID":1500,"Age":65,"Area Income":50792.08973},{"ID":1501,"Age":73,"Area Income":52199.8553},{"ID":1502,"Age":70,"Area Income":44474.37665},{"ID":1503,"Age":72,"Area Income":38555.2153},{"ID":1504,"Age":66,"Area Income":44792.11514},{"ID":1505,"Age":77,"Area Income":54849.18543},{"ID":1506,"Age":67,"Area Income":32411.47134},{"ID":1507,"Age":69,"Area Income":53490.96284},{"ID":1508,"Age":77,"Area Income":44424.62219},{"ID":1509,"Age":70,"Area Income":46466.8199},{"ID":1510,"Age":69,"Area Income":54245.28264},{"ID":1511,"Age":72,"Area Income":39406.7568},{"ID":1512,"Age":72,"Area Income":57244.24161},{"ID":1513,"Age":67,"Area Income":51203.95497},{"ID":1514,"Age":76,"Area Income":38075.12863},{"ID":1515,"Age":74,"Area Income":46865.6047},{"ID":1516,"Age":73,"Area Income":36158.70456},{"ID":1517,"Age":77,"Area Income":46064.15522},{"ID":1518,"Age":73,"Area Income":47124.95582},{"ID":1519,"Age":68,"Area Income":57840.80457},{"ID":1520,"Age":72,"Area Income":40028.95547},{"ID":1521,"Age":70,"Area Income":42386.95757},{"ID":1522,"Age":76,"Area Income":39360.75534},{"ID":1523,"Age":69,"Area Income":56223.24716},{"ID":1524,"Age":66,"Area Income":45517.19508},{"ID":1525,"Age":77,"Area Income":48072.87281},{"ID":1526,"Age":67,"Area Income":37727.05685},{"ID":1527,"Age":71,"Area Income":39891.88341},{"ID":1528,"Age":78,"Area Income":34431.55041},{"ID":1529,"Age":71,"Area Income":48048.06632},{"ID":1530,"Age":67,"Area Income":55405.50444},{"ID":1531,"Age":70,"Area Income":52791.28404},{"ID":1532,"Age":74,"Area Income":31753.69835},{"ID":1533,"Age":75,"Area Income":52575.54981},{"ID":1534,"Age":73,"Area Income":51565.5105},{"ID":1535,"Age":67,"Area Income":48957.38364},{"ID":1536,"Age":65,"Area Income":34869.60468},{"ID":1537,"Age":73,"Area Income":58506.85357},{"ID":1538,"Age":77,"Area Income":45171.56487},{"ID":1539,"Age":68,"Area Income":30441.56652},{"ID":1540,"Age":79,"Area Income":49209.7559},{"ID":1541,"Age":80,"Area Income":37428.52771},{"ID":1542,"Age":66,"Area Income":44948.67878},{"ID":1543,"Age":69,"Area Income":53489.01387},{"ID":1544,"Age":72,"Area Income":32844.13161},{"ID":1545,"Age":76,"Area Income":50859.68775},{"ID":1546,"Age":79,"Area Income":52456.31521},{"ID":1547,"Age":78,"Area Income":31336.65601},{"ID":1548,"Age":73,"Area Income":45120.01187},{"ID":1549,"Age":79,"Area Income":41761.04293},{"ID":1550,"Age":67,"Area Income":43489.46193},{"ID":1551,"Age":65,"Area Income":36385.71661},{"ID":1552,"Age":70,"Area Income":31321.01554},{"ID":1553,"Age":67,"Area Income":46344.40162},{"ID":1554,"Age":70,"Area Income":44715.83819},{"ID":1555,"Age":74,"Area Income":42884.64434},{"ID":1556,"Age":78,"Area Income":58527.04507},{"ID":1557,"Age":79,"Area Income":51003.98213},{"ID":1558,"Age":79,"Area Income":47077.36929},{"ID":1559,"Age":70,"Area Income":58720.66844},{"ID":1560,"Age":66,"Area Income":58747.94504},{"ID":1561,"Age":65,"Area Income":32533.03086},{"ID":1562,"Age":76,"Area Income":41642.00898},{"ID":1563,"Age":72,"Area Income":59055.85454},{"ID":1564,"Age":66,"Area Income":42784.69802},{"ID":1565,"Age":79,"Area Income":30899.21727},{"ID":1566,"Age":65,"Area Income":55383.27921},{"ID":1567,"Age":65,"Area Income":31393.48197},{"ID":1568,"Age":75,"Area Income":53347.57004},{"ID":1569,"Age":70,"Area Income":32164.45465},{"ID":1570,"Age":65,"Area Income":47474.54951},{"ID":1571,"Age":68,"Area Income":46315.71531},{"ID":1572,"Age":80,"Area Income":47353.11827},{"ID":1573,"Age":76,"Area Income":44870.60396},{"ID":1574,"Age":66,"Area Income":59473.22473},{"ID":1575,"Age":79,"Area Income":33094.47245},{"ID":1576,"Age":74,"Area Income":57962.36727},{"ID":1577,"Age":67,"Area Income":37779.03618},{"ID":1578,"Age":79,"Area Income":34686.00782},{"ID":1579,"Age":73,"Area Income":34956.1224},{"ID":1580,"Age":65,"Area Income":38154.17803},{"ID":1581,"Age":70,"Area Income":33768.71329},{"ID":1582,"Age":70,"Area Income":37334.73681},{"ID":1583,"Age":73,"Area Income":35671.31305},{"ID":1584,"Age":67,"Area Income":56537.96713},{"ID":1585,"Age":72,"Area Income":38153.73199},{"ID":1586,"Age":76,"Area Income":31024.17803},{"ID":1587,"Age":70,"Area Income":51793.68919},{"ID":1588,"Age":69,"Area Income":43025.0935},{"ID":1589,"Age":66,"Area Income":31200.54853},{"ID":1590,"Age":74,"Area Income":35010.22961},{"ID":1591,"Age":79,"Area Income":57532.29773},{"ID":1592,"Age":79,"Area Income":35122.31948},{"ID":1593,"Age":69,"Area Income":32415.45264},{"ID":1594,"Age":80,"Area Income":51192.23865},{"ID":1595,"Age":70,"Area Income":48631.71779},{"ID":1596,"Age":79,"Area Income":34945.30893},{"ID":1597,"Age":77,"Area Income":48104.08715},{"ID":1598,"Age":73,"Area Income":36811.92168},{"ID":1599,"Age":70,"Area Income":31067.37524},{"ID":1600,"Age":67,"Area Income":39307.09612},{"ID":1601,"Age":70,"Area Income":50921.25708},{"ID":1602,"Age":69,"Area Income":49308.04211},{"ID":1603,"Age":72,"Area Income":45960.30075},{"ID":1604,"Age":75,"Area Income":57192.84357},{"ID":1605,"Age":67,"Area Income":53493.2725},{"ID":1606,"Age":75,"Area Income":53135.3962},{"ID":1607,"Age":76,"Area Income":46585.53292},{"ID":1608,"Age":68,"Area Income":57825.85253},{"ID":1609,"Age":76,"Area Income":48269.52264},{"ID":1610,"Age":73,"Area Income":59782.91515},{"ID":1611,"Age":65,"Area Income":58228.2241},{"ID":1612,"Age":75,"Area Income":35583.44873},{"ID":1613,"Age":77,"Area Income":36660.77746},{"ID":1614,"Age":69,"Area Income":30710.53968},{"ID":1615,"Age":78,"Area Income":44583.85867},{"ID":1616,"Age":72,"Area Income":50364.98578},{"ID":1617,"Age":68,"Area Income":45795.80364},{"ID":1618,"Age":76,"Area Income":38588.75158},{"ID":1619,"Age":70,"Area Income":33634.82771},{"ID":1620,"Age":75,"Area Income":44655.89457},{"ID":1621,"Age":67,"Area Income":30174.6807},{"ID":1622,"Age":71,"Area Income":51236.44337},{"ID":1623,"Age":74,"Area Income":38955.53132},{"ID":1624,"Age":69,"Area Income":56640.50671},{"ID":1625,"Age":73,"Area Income":51365.71906},{"ID":1626,"Age":73,"Area Income":52367.66578},{"ID":1627,"Age":72,"Area Income":58842.63806},{"ID":1628,"Age":72,"Area Income":34413.35452},{"ID":1629,"Age":72,"Area Income":35798.64111},{"ID":1630,"Age":66,"Area Income":36162.93545},{"ID":1631,"Age":65,"Area Income":46159.13355},{"ID":1632,"Age":68,"Area Income":39320.06782},{"ID":1633,"Age":71,"Area Income":41160.79631},{"ID":1634,"Age":67,"Area Income":48318.70601},{"ID":1635,"Age":68,"Area Income":48984.00192},{"ID":1636,"Age":73,"Area Income":34241.13113},{"ID":1637,"Age":69,"Area Income":42769.73467},{"ID":1638,"Age":73,"Area Income":45812.75995}]